{"title":"Rebellion - Arminius: Furor Teutonicus (2012) mp3@320","uid":7776756,"size":143971547,"categoryP":"audio","categoryS":"music","magnet":"?xt=urn:btih:0485771dd47b6671f645ebc2ed65720fc8649ee4&amp;dn=Rebellion+-+Arminius%3A+Furor+Teutonicus+%282012%29+mp3%40320&amp;tr=udp%3A%2F%2Ftracker.openbittorrent.com%3A80&amp;tr=udp%3A%2F%2Fopen.demonii.com%3A1337&amp;tr=udp%3A%2F%2Ftracker.coppersurfer.tk%3A6969&amp;tr=udp%3A%2F%2Fexodus.desync.com%3A6969","seeders":2,"leechers":0,"uploader":"Knazi","files":-1,"time":1351675676,"description":"Country: Germany\nGenre: Heavy/Power Metal\nType: Full-length\nRelease date: October 26th, 2012\nLabel: Massacre Records\nTT: 59:28\n\n\n01. \tRest In Peace             06:52\n02. \tAla Germanica             04:05\n03. \tPrince Of The Cheruscer   04:38\n04. \tDusk Awaiting Dawn        05:23\n05. \tBreeding Hate             04:25\n06. \tThe Seeress Tower         06:33\n07. \tVarus                     04:30\n08. \tThe Tribes United         04:08\n09. \tGhost Of Freedom          05:00\n10. \tFuror Teutonicus          04:09\n11. \tVae Victis                04:25\n12. \tRequiem                   05:20","torrent":{"xt":"urn:btih:0485771dd47b6671f645ebc2ed65720fc8649ee4","amp;dn":"Rebellion+-+Arminius%3A+Furor+Teutonicus+%282012%29+mp3%40320","amp;tr":["udp%3A%2F%2Ftracker.openbittorrent.com%3A80","udp%3A%2F%2Fopen.demonii.com%3A1337","udp%3A%2F%2Ftracker.coppersurfer.tk%3A6969","udp%3A%2F%2Fexodus.desync.com%3A6969"],"infoHash":"0485771dd47b6671f645ebc2ed65720fc8649ee4","infoHashBuffer":{"type":"Buffer","data":[4,133,119,29,212,123,102,113,246,69,235,194,237,101,114,15,200,100,158,228]},"announce":[],"urlList":[]}}