{"title":"Private.Sex.Auditions.11.Private.Auditions.X.XXX.720p.WEBRip.MP4","uid":12459740,"size":5897003607,"categoryP":"porn","categoryS":"movies","magnet":"?xt=urn:btih:211bf29769c8a60bc2b84ebdbce278f9118593b4&amp;dn=Private.Sex.Auditions.11.Private.Auditions.X.XXX.720p.WEBRip.MP4&amp;tr=udp%3A%2F%2Ftracker.openbittorrent.com%3A80&amp;tr=udp%3A%2F%2Fopen.demonii.com%3A1337&amp;tr=udp%3A%2F%2Ftracker.coppersurfer.tk%3A6969&amp;tr=udp%3A%2F%2Fexodus.desync.com%3A6969","seeders":2,"leechers":7,"uploader":"0-DayXXX","files":1,"time":1442788412,"description":"---------------------------------------\nPrivate.Sex.Auditions.11.Private.Auditions.X.XXX.720p.WEBRip.MP4-VSEX\n---------------------------------------\nScreenshot(s): &lt;a href=&quot;\nhttp://imgsay.com/?v=900053.jpg&quot; rel=&quot;nofollow&quot; target=&quot;_NEW&quot;&gt;\nhttp://imgsay.com/?v=900053.jpg&lt;/a&gt;\n\n---------------------------------------\nFormat:\t\tMPEG-4\nSize:\t\t5.49 GiB\nDuration:\t2h 57min\nResolution:\t1280x720\nBitrate:\t4285Kbps\n---------------------------------------\nIf you like this torrent, please post a comment!\n\nDon't forget to seed!","torrent":{"xt":"urn:btih:211bf29769c8a60bc2b84ebdbce278f9118593b4","amp;dn":"Private.Sex.Auditions.11.Private.Auditions.X.XXX.720p.WEBRip.MP4","amp;tr":["udp%3A%2F%2Ftracker.openbittorrent.com%3A80","udp%3A%2F%2Fopen.demonii.com%3A1337","udp%3A%2F%2Ftracker.coppersurfer.tk%3A6969","udp%3A%2F%2Fexodus.desync.com%3A6969"],"infoHash":"211bf29769c8a60bc2b84ebdbce278f9118593b4","infoHashBuffer":{"type":"Buffer","data":[33,27,242,151,105,200,166,11,194,184,78,189,188,226,120,249,17,133,147,180]},"announce":[],"urlList":[]}}