{"title":"KKlixenProductions - Jessyca Swan - Teasing Tongues 10","uid":12289017,"size":587317261,"categoryP":"porn","categoryS":"movie_clips","magnet":"?xt=urn:btih:2848b7aab7f99129481b4a3e098f300547d1068c&amp;dn=KKlixenProductions+-+Jessyca+Swan+-+Teasing+Tongues+10&amp;tr=udp%3A%2F%2Ftracker.openbittorrent.com%3A80&amp;tr=udp%3A%2F%2Fopen.demonii.com%3A1337&amp;tr=udp%3A%2F%2Ftracker.coppersurfer.tk%3A6969&amp;tr=udp%3A%2F%2Fexodus.desync.com%3A6969","seeders":2,"leechers":1,"uploader":"Ctrlme","files":1,"time":1440521643,"description":"-----------------------------------------------------------\nKKlixenProductions - Jessyca Swan - Teasing Tongues 10\n-----------------------------------------------------------\nScreenshots: &lt;a href=&quot;\nhttp://imgctrl.com/image/NOj&quot; rel=&quot;nofollow&quot; target=&quot;_NEW&quot;&gt;\nhttp://imgctrl.com/image/NOj&lt;/a&gt; &lt;a href=&quot;\nhttp://imgctrl.com/image/NOn&quot; rel=&quot;nofollow&quot; target=&quot;_NEW&quot;&gt;\nhttp://imgctrl.com/image/NOn&lt;/a&gt;\n-----------------------------------------------------------\nCategory:  Blowjob\nSize: 587317261 bytes (560.11 MiB), duration: 00:36:56, avg.bitrate: 2120 kb/s\nAudio: aac, 44100 Hz, 2 channels, s16, 95 kb/s (ger)\nVideo: h264, yuv420p, 852x480, 2018 kb/s, 29.97 fpsÂ® (ger)\n-----------------------------------------------------------\nIf you like this torrent, please post a comment!\n\nDon't forget to seed!","torrent":{"xt":"urn:btih:2848b7aab7f99129481b4a3e098f300547d1068c","amp;dn":"KKlixenProductions+-+Jessyca+Swan+-+Teasing+Tongues+10","amp;tr":["udp%3A%2F%2Ftracker.openbittorrent.com%3A80","udp%3A%2F%2Fopen.demonii.com%3A1337","udp%3A%2F%2Ftracker.coppersurfer.tk%3A6969","udp%3A%2F%2Fexodus.desync.com%3A6969"],"infoHash":"2848b7aab7f99129481b4a3e098f300547d1068c","infoHashBuffer":{"type":"Buffer","data":[40,72,183,170,183,249,145,41,72,27,74,62,9,143,48,5,71,209,6,140]},"announce":[],"urlList":[]}}