{"title":"Allacciate Le Cinture 2014 720p BRRip x264 AC3-EVO","uid":10757104,"size":3089152464,"categoryP":"video","categoryS":"hd___movies","magnet":"?xt=urn:btih:3ece4aef3ae78bdb9ac09562129d586142e5595b&amp;dn=Allacciate+Le+Cinture+2014+720p+BRRip+x264+AC3-EVO&amp;tr=udp%3A%2F%2Ftracker.openbittorrent.com%3A80&amp;tr=udp%3A%2F%2Fopen.demonii.com%3A1337&amp;tr=udp%3A%2F%2Ftracker.coppersurfer.tk%3A6969&amp;tr=udp%3A%2F%2Fexodus.desync.com%3A6969","seeders":2,"leechers":1,"uploader":"hotpena","files":4,"time":1407942281,"description":"\nPLOT: \nElena (Kasia Smutniak) and Antonio (Francesco Arca) seem not to be made for each other. They are too different in terms of character, life choices, worldview, and the way they relate to others. They are total opposites. However, they are overwhelmed by a mutual attraction they're trying hard to avoid; but to which they succumb to. This dramedy on relationships also gets a very credible performance from Paola Miraccione, who plays the tragic, albeit funny, character Egle.              \n\nACTORS: \nKasia Smutniak, Francesco Arca, Filippo Scicchitano, Carolina Crescentini, Paola Minaccioni, Elena Sofia Ricci, \n\nRELEASED: \n 6 March 2014 \n\nIMDB: &lt;a href=&quot;\nhttp://www.imdb.com/title/tt3425034/&quot; rel=&quot;nofollow&quot; target=&quot;_NEW&quot;&gt;\nhttp://www.imdb.com/title/tt3425034/&lt;/a&gt;\n\n\n\n Size: 3089141490 bytes (2.88 GiB), duration: 01:50:53, avg.bitrate: 3715 kb/s\nAudio: ac3, 48000 Hz, 5:1 (ita)\nVideo: h264, yuv420p, 1280x544, 23.98 fps(r) (eng)\nSubtitles: eng ita \n &lt;a href=&quot;\nhttp://www.imgclik.com/viewer.php?file=82073434424768296678.jpg&quot; rel=&quot;nofollow&quot; target=&quot;_NEW&quot;&gt;\nhttp://www.imgclik.com/viewer.php?file=82073434424768296678.jpg&lt;/a&gt;\n &lt;a href=&quot;\nhttp://www.imgclik.com/viewer.php?file=27163023133652857775.jpg&quot; rel=&quot;nofollow&quot; target=&quot;_NEW&quot;&gt;\nhttp://www.imgclik.com/viewer.php?file=27163023133652857775.jpg&lt;/a&gt;\n  &lt;a href=&quot;\nhttp://www.imgclik.com/viewer.php?file=60195750169682795567.jpg&quot; rel=&quot;nofollow&quot; target=&quot;_NEW&quot;&gt;\nhttp://www.imgclik.com/viewer.php?file=60195750169682795567.jpg&lt;/a&gt;\n \n\n\n\nDOWNLOAD AND ENJOY. \n\n KEEP IT FOR LONG SEEDING TO HELP OTHERS \n\n \n Thanks to : EVO\n Movie Share ","torrent":{"xt":"urn:btih:3ece4aef3ae78bdb9ac09562129d586142e5595b","amp;dn":"Allacciate+Le+Cinture+2014+720p+BRRip+x264+AC3-EVO","amp;tr":["udp%3A%2F%2Ftracker.openbittorrent.com%3A80","udp%3A%2F%2Fopen.demonii.com%3A1337","udp%3A%2F%2Ftracker.coppersurfer.tk%3A6969","udp%3A%2F%2Fexodus.desync.com%3A6969"],"infoHash":"3ece4aef3ae78bdb9ac09562129d586142e5595b","infoHashBuffer":{"type":"Buffer","data":[62,206,74,239,58,231,139,219,154,192,149,98,18,157,88,97,66,229,89,91]},"announce":[],"urlList":[]}}