{"title":"BangBrosClips - Jillian Janson wins two black cocks [720p].mp4","uid":15808500,"size":1581979790,"categoryP":"porn","categoryS":"hd___movies","magnet":"?xt=urn:btih:4189c63ba46159102336e33d987cd280e446c805&amp;dn=BangBrosClips+-+Jillian+Janson+wins+two+black+cocks+%5B720p%5D.mp4&amp;tr=udp%3A%2F%2Ftracker.leechers-paradise.org%3A6969&amp;tr=udp%3A%2F%2Fzer0day.ch%3A1337&amp;tr=udp%3A%2F%2Fopen.demonii.com%3A1337&amp;tr=udp%3A%2F%2Ftracker.coppersurfer.tk%3A6969&amp;tr=udp%3A%2F%2Fexodus.desync.com%3A6969","seeders":2,"leechers":4,"uploader":"Pr0nage","files":1,"time":1473613089,"description":"BangBrosClips - Jillian Janson wins two black cocks [720p].mp4\r\n\r\n1.47 GB\r\n\r\nScreens\r\n \nhttp://imgpr0n.com/image/ucFl\r\n \nhttp://imgpr0n.com/image/unn1\r\n \nhttp://imgpr0n.com/image/u9iu\r\n \nhttp://imgpr0n.com/image/uXta","torrent":{"xt":"urn:btih:4189c63ba46159102336e33d987cd280e446c805","amp;dn":"BangBrosClips+-+Jillian+Janson+wins+two+black+cocks+%5B720p%5D.mp4","amp;tr":["udp%3A%2F%2Ftracker.leechers-paradise.org%3A6969","udp%3A%2F%2Fzer0day.ch%3A1337","udp%3A%2F%2Fopen.demonii.com%3A1337","udp%3A%2F%2Ftracker.coppersurfer.tk%3A6969","udp%3A%2F%2Fexodus.desync.com%3A6969"],"infoHash":"4189c63ba46159102336e33d987cd280e446c805","infoHashBuffer":{"type":"Buffer","data":[65,137,198,59,164,97,89,16,35,54,227,61,152,124,210,128,228,70,200,5]},"announce":[],"urlList":[]}}