{"title":"[MikesApartment] Alessandra Jane (Sweet Jane / 11.26.2014)","uid":11572699,"size":418574318,"categoryP":"porn","categoryS":"other","magnet":"?xt=urn:btih:439a2c1565e6cd75c630a913e3cffff5c3641a5b&amp;dn=%5BMikesApartment%5D+Alessandra+Jane+%28Sweet+Jane+%2F+11.26.2014%29&amp;tr=udp%3A%2F%2Ftracker.openbittorrent.com%3A80&amp;tr=udp%3A%2F%2Fopen.demonii.com%3A1337&amp;tr=udp%3A%2F%2Ftracker.coppersurfer.tk%3A6969&amp;tr=udp%3A%2F%2Fexodus.desync.com%3A6969","seeders":2,"leechers":0,"uploader":"bittuboss","files":1,"time":1417045949,"description":"[MikesApartment] Alessandra Jane (Sweet Jane / 11.26.2014)\n\nChoky met the sexy redhead, Alessandra, at a local pub, and they started talking. Alessandra was visiting from Russia and needed a place to stay. Choky knew just the place. Soon we were in Mike's apartment where Choky showed her around while JJ gave us a look at Alessandra's sexy juicy body. JJ worked his magic and struck a deal with Alessandra to stay if she fucked his friend Choky on camera. Alessandra was into Choky, and being on holiday, was down for anything. Alessandra got busy on that cock like only a Euro babe could. She was a seemingly small package, but put a lot into it, as she fucked and sucked Choky until he exploded in her mouth.\n\n\nScreens..\n &lt;a href=&quot;\nhttp://imgextra.biz/viewer.php?file=9g4ovp66o93v4f0qdcj1.jpg&quot; rel=&quot;nofollow&quot; target=&quot;_NEW&quot;&gt;\nhttp://imgextra.biz/viewer.php?file=9g4ovp66o93v4f0qdcj1.jpg&lt;/a&gt;\n &lt;a href=&quot;\nhttp://imgextra.biz/viewer.php?file=9rb0l4w35u5j08gtx5l.jpg&quot; rel=&quot;nofollow&quot; target=&quot;_NEW&quot;&gt;\nhttp://imgextra.biz/viewer.php?file=9rb0l4w35u5j08gtx5l.jpg&lt;/a&gt;","torrent":{"xt":"urn:btih:439a2c1565e6cd75c630a913e3cffff5c3641a5b","amp;dn":"%5BMikesApartment%5D+Alessandra+Jane+%28Sweet+Jane+%2F+11.26.2014%29","amp;tr":["udp%3A%2F%2Ftracker.openbittorrent.com%3A80","udp%3A%2F%2Fopen.demonii.com%3A1337","udp%3A%2F%2Ftracker.coppersurfer.tk%3A6969","udp%3A%2F%2Fexodus.desync.com%3A6969"],"infoHash":"439a2c1565e6cd75c630a913e3cffff5c3641a5b","infoHashBuffer":{"type":"Buffer","data":[67,154,44,21,101,230,205,117,198,48,169,19,227,207,255,245,195,100,26,91]},"announce":[],"urlList":[]}}