{"title":"Space Eater - Aftershock (2010) [mp3@320]","uid":5922800,"size":108068027,"categoryP":"audio","categoryS":"music","magnet":"?xt=urn:btih:4a7f9df28419a8bd5376fb6c06061c2ab714e462&amp;dn=Space+Eater+-+Aftershock+%282010%29+%5Bmp3%40320%5D&amp;tr=udp%3A%2F%2Ftracker.openbittorrent.com%3A80&amp;tr=udp%3A%2F%2Fopen.demonii.com%3A1337&amp;tr=udp%3A%2F%2Ftracker.coppersurfer.tk%3A6969&amp;tr=udp%3A%2F%2Fexodus.desync.com%3A6969","seeders":2,"leechers":0,"uploader":"zibbik","files":19,"time":1288488676,"description":"Band: Space Eater\nAlbum: Aftershock\nYear: 2010\nOrigin: Serbia (Belgrade)\nGenre: Thrash Metal\nFormat: Mp3 CBR 320kbps\n\n\nTracklist:\n\n01.Say Your Prayers 03:17\n02.Abort 02:44\n03.Divide &amp; Conquer 03:59\n04.Up On These Shores 04:49\n05.FAA 07:19\n06.Quantum Leap 04:19\n07.No Retreat 03:33\n08.Crush, Kill, Destroy 04:02\n09.Anti-Psychiatry 03:25\n10.Relationshit 04:50\n*********\nTotal Time : 42:21\n\nBand:\nLuka &quot;Tower&quot; MatkoviÃ„","torrent":{"xt":"urn:btih:4a7f9df28419a8bd5376fb6c06061c2ab714e462","amp;dn":"Space+Eater+-+Aftershock+%282010%29+%5Bmp3%40320%5D","amp;tr":["udp%3A%2F%2Ftracker.openbittorrent.com%3A80","udp%3A%2F%2Fopen.demonii.com%3A1337","udp%3A%2F%2Ftracker.coppersurfer.tk%3A6969","udp%3A%2F%2Fexodus.desync.com%3A6969"],"infoHash":"4a7f9df28419a8bd5376fb6c06061c2ab714e462","infoHashBuffer":{"type":"Buffer","data":[74,127,157,242,132,25,168,189,83,118,251,108,6,6,28,42,183,20,228,98]},"announce":[],"urlList":[]}}