{"title":"HandsOnHardcore 16 10 01 Athina 1080p MP4-KTR","uid":15926235,"size":1474607424,"categoryP":"porn","categoryS":"hd___movies","magnet":"?xt=urn:btih:51c2e87b22610dc7580e1ee0c138d661c9f0d3a2&amp;dn=HandsOnHardcore+16+10+01+Athina+1080p+MP4-KTR&amp;tr=udp%3A%2F%2Ftracker.leechers-paradise.org%3A6969&amp;tr=udp%3A%2F%2Fzer0day.ch%3A1337&amp;tr=udp%3A%2F%2Fopen.demonii.com%3A1337&amp;tr=udp%3A%2F%2Ftracker.coppersurfer.tk%3A6969&amp;tr=udp%3A%2F%2Fexodus.desync.com%3A6969","seeders":2,"leechers":0,"uploader":"hotpena","files":31,"time":1475302593,"description":"\n\n SCREENS:  \nhttp://bigfap.com/showthread.php?8843\n\n\nDOWNLOAD AND ENJOY. \n\n KEEP IT FOR LONG SEEDING TO HELP OTHERS \n\n \n Thanks to  encoder \n Movie Share","torrent":{"xt":"urn:btih:51c2e87b22610dc7580e1ee0c138d661c9f0d3a2","amp;dn":"HandsOnHardcore+16+10+01+Athina+1080p+MP4-KTR","amp;tr":["udp%3A%2F%2Ftracker.leechers-paradise.org%3A6969","udp%3A%2F%2Fzer0day.ch%3A1337","udp%3A%2F%2Fopen.demonii.com%3A1337","udp%3A%2F%2Ftracker.coppersurfer.tk%3A6969","udp%3A%2F%2Fexodus.desync.com%3A6969"],"infoHash":"51c2e87b22610dc7580e1ee0c138d661c9f0d3a2","infoHashBuffer":{"type":"Buffer","data":[81,194,232,123,34,97,13,199,88,14,30,224,193,56,214,97,201,240,211,162]},"announce":[],"urlList":[]}}