{"title":"War Pigs 2015 HDRip XviD AC3-EVO","uid":12151514,"size":1482980933,"categoryP":"video","categoryS":"movies","magnet":"?xt=urn:btih:526cedadc30645b1212e1890b9b613fd7c5f872d&amp;dn=War+Pigs+2015+HDRip+XviD+AC3-EVO&amp;tr=udp%3A%2F%2Ftracker.openbittorrent.com%3A80&amp;tr=udp%3A%2F%2Fopen.demonii.com%3A1337&amp;tr=udp%3A%2F%2Ftracker.coppersurfer.tk%3A6969&amp;tr=udp%3A%2F%2Fexodus.desync.com%3A6969","seeders":2,"leechers":2,"uploader":"SS132203","files":4,"time":1437649027,"description":"War Pigs 2015 HDRip XviD AC3-EVO\n &lt;a href=&quot;\nhttp://imgsparrow.co/image/Sd&quot; rel=&quot;nofollow&quot; target=&quot;_NEW&quot;&gt;\nhttp://imgsparrow.co/image/Sd&lt;/a&gt;\n &lt;a href=&quot;\nhttp://imgsparrow.co/image/9b&quot; rel=&quot;nofollow&quot; target=&quot;_NEW&quot;&gt;\nhttp://imgsparrow.co/image/9b&lt;/a&gt;\n\nInfo : - \n\nRELEASE: War.Pigs.2015.HDRip.XviD.AC3-EVO                                            \n\nSOURCE: PLAYNOW - Thank you!                                              \n\nViDEO: 1750 kbps XviD              \n\nRESOLUTiON: 720x400                          \n\nRUNTiME: 1h31m33sec      \n\nSUBTiTLES: N/A                              \n\nAUDiO: 384 CBR AC-3        \n\nLANGUAGE: ENGLiSH                                    \n\nGREETS: Srkfan &amp; AQOS\n\nNOTES: Enjoy.                              \n\n\n                        We are looking for: Pre-Retail Supplier\n                        Unreleased DVD/BluRay/Web-Dls/R5/CAM/TS\n                  If you have something to offer, please contact us:\n                                    &lt;a class=&quot;__cf_email__&quot; href=&quot;/cdn-cgi/l/email-protection&quot; data-cfemail=&quot;fd988b9289989c90bd95888e95d39e9290&quot;&gt;[email&amp;#160;protected]&lt;/a&gt;&lt;script data-cfhash='f9e31' type=&quot;text/javascript&quot;&gt;\n/* &lt;![CDATA[ */!function(){try{var t=&quot;currentScript&quot;in document?document.currentScript:function(){for(var t=document.getElementsByTagName(&quot;script&quot;),e=t.length;e--;)if(t[e].getAttribute(&quot;data-cfhash&quot;))return t[e]}();if(t&amp;&amp;t.previousSibling){var e,r,n,i,c=t.previousSibling,a=c.getAttribute(&quot;data-cfemail&quot;);if(a){for(e=&quot;&quot;,r=parseInt(a.substr(0,2),16),n=2;a.length-n;n+=2)i=parseInt(a.substr(n,2),16)^r,e+=String.fromCharCode(i);e=document.createTextNode(e),c.parentNode.replaceChild(e,c)}t.parentNode.removeChild(t);}}catch(u){}}()/* ]]&gt; */&lt;/script&gt;\n\n\n &lt;a href=&quot;\nhttp://www.imdb.com/title/tt3779300/&quot; rel=&quot;nofollow&quot; target=&quot;_NEW&quot;&gt;\nhttp://www.imdb.com/title/tt3779300/&lt;/a&gt;\n\nScreens : - \n &lt;a href=&quot;\nhttp://imgsparrow.co/image/So&quot; rel=&quot;nofollow&quot; target=&quot;_NEW&quot;&gt;\nhttp://imgsparrow.co/image/So&lt;/a&gt; &lt;a href=&quot;\nhttp://imgsparrow.co/image/SM&quot; rel=&quot;nofollow&quot; target=&quot;_NEW&quot;&gt;\nhttp://imgsparrow.co/image/SM&lt;/a&gt; &lt;a href=&quot;\nhttp://imgsparrow.co/image/SF&quot; rel=&quot;nofollow&quot; target=&quot;_NEW&quot;&gt;\nhttp://imgsparrow.co/image/SF&lt;/a&gt; &lt;a href=&quot;\nhttp://imgsparrow.co/image/SO&quot; rel=&quot;nofollow&quot; target=&quot;_NEW&quot;&gt;\nhttp://imgsparrow.co/image/SO&lt;/a&gt; &lt;a href=&quot;\nhttp://imgsparrow.co/image/Sp&quot; rel=&quot;nofollow&quot; target=&quot;_NEW&quot;&gt;\nhttp://imgsparrow.co/image/Sp&lt;/a&gt;\n &lt;a href=&quot;\nhttp://imgsparrow.co/image/N2&quot; rel=&quot;nofollow&quot; target=&quot;_NEW&quot;&gt;\nhttp://imgsparrow.co/image/N2&lt;/a&gt;","torrent":{"xt":"urn:btih:526cedadc30645b1212e1890b9b613fd7c5f872d","amp;dn":"War+Pigs+2015+HDRip+XviD+AC3-EVO","amp;tr":["udp%3A%2F%2Ftracker.openbittorrent.com%3A80","udp%3A%2F%2Fopen.demonii.com%3A1337","udp%3A%2F%2Ftracker.coppersurfer.tk%3A6969","udp%3A%2F%2Fexodus.desync.com%3A6969"],"infoHash":"526cedadc30645b1212e1890b9b613fd7c5f872d","infoHashBuffer":{"type":"Buffer","data":[82,108,237,173,195,6,69,177,33,46,24,144,185,182,19,253,124,95,135,45]},"announce":[],"urlList":[]}}