{"title":"Luni Coleone Presents Wanted Record Or Live (Double Impact_Editi","uid":5386996,"size":127852358,"categoryP":"audio","categoryS":"music","magnet":"?xt=urn:btih:5c71b8c1e63619482753e17e5fcb81a21365d098&amp;dn=Luni+Coleone+Presents+Wanted+Record+Or+Live+%28Double+Impact_Editi&amp;tr=udp%3A%2F%2Ftracker.openbittorrent.com%3A80&amp;tr=udp%3A%2F%2Fopen.demonii.com%3A1337&amp;tr=udp%3A%2F%2Ftracker.coppersurfer.tk%3A6969&amp;tr=udp%3A%2F%2Fexodus.desync.com%3A6969","seeders":2,"leechers":0,"uploader":"aszeran","files":32,"time":1266884352,"description":"Disc 1\n\n1. Intro\n2. Pimp Sh*T\n3. We Ride - (with I-Rocc)\n4. On the Real\n5. West Coast Thugs\n6. Where You at?\n7. Crip Party - (with T-Nutty)\n8. Ride With the Game - (with T-Nutty)\n9. (Skit)\n10. Life\n11. Gansta - (with Keak Da Sneak/Daz Dillinger)\n12. Soulja\n13. I Mic - (with AP-9)\n14. Last Days\n15. Love 4 My Thugs - (with Devious)\n16. Outro\n\n\nDisc 2\n\n1. Home Run\n2. My Name\n3. Why?\n4. I'll Smoke Anybody\n5. Grab That Cannon\n6. Streets Is Watchin', The\n7. Kick It\n8. Keep Me Comin' 2 You\n9. Hold Me Down - (with Mae Gee)\n10. Woodgrain - (with Young Savage/Lace Leno)\n11. I Want 2 Meet You\n12. Get Off Me (Skit)\n13. Get Off Me\n14. Gansta till I Die - (with Big Hollis)\n15. Miss Purdy","torrent":{"xt":"urn:btih:5c71b8c1e63619482753e17e5fcb81a21365d098","amp;dn":"Luni+Coleone+Presents+Wanted+Record+Or+Live+%28Double+Impact_Editi","amp;tr":["udp%3A%2F%2Ftracker.openbittorrent.com%3A80","udp%3A%2F%2Fopen.demonii.com%3A1337","udp%3A%2F%2Ftracker.coppersurfer.tk%3A6969","udp%3A%2F%2Fexodus.desync.com%3A6969"],"infoHash":"5c71b8c1e63619482753e17e5fcb81a21365d098","infoHashBuffer":{"type":"Buffer","data":[92,113,184,193,230,54,25,72,39,83,225,126,95,203,129,162,19,101,208,152]},"announce":[],"urlList":[]}}