{"title":"College Rules - Crazy College Orgy HD 720p","uid":8722136,"size":1150051181,"categoryP":"porn","categoryS":"hd___movies","magnet":"?xt=urn:btih:6c66b5d12ab1a951e79e6c20360f935dbeb5d9e6&amp;dn=College+Rules+-+Crazy+College+Orgy+HD+720p&amp;tr=udp%3A%2F%2Ftracker.openbittorrent.com%3A80&amp;tr=udp%3A%2F%2Fopen.demonii.com%3A1337&amp;tr=udp%3A%2F%2Ftracker.coppersurfer.tk%3A6969&amp;tr=udp%3A%2F%2Fexodus.desync.com%3A6969","seeders":2,"leechers":0,"uploader":"irealu69","files":-1,"time":1374440343,"description":"College Rules - Crazy College Orgy HD 720p\n~~~~~~~~~~~~~~~~~~~~~~~~~~~~~~~~~~~~~~~~~~\n\nScreenshots:\n~~~~~~~~~~~~\n &lt;a href=&quot;\nhttp://picturescream.com/x/clean/o1p&quot; rel=&quot;nofollow&quot; target=&quot;_NEW&quot;&gt;\nhttp://picturescream.com/x/clean/o1p&lt;/a&gt;\n &lt;a href=&quot;\nhttp://picturescream.com/x/clean/o14&quot; rel=&quot;nofollow&quot; target=&quot;_NEW&quot;&gt;\nhttp://picturescream.com/x/clean/o14&lt;/a&gt;\n &lt;a href=&quot;\nhttp://picturescream.com/x/clean/o18&quot; rel=&quot;nofollow&quot; target=&quot;_NEW&quot;&gt;\nhttp://picturescream.com/x/clean/o18&lt;/a&gt;\n &lt;a href=&quot;\nhttp://picturescream.com/x/clean/o1D&quot; rel=&quot;nofollow&quot; target=&quot;_NEW&quot;&gt;\nhttp://picturescream.com/x/clean/o1D&lt;/a&gt;\n &lt;a href=&quot;\nhttp://picturescream.com/x/clean/o1U&quot; rel=&quot;nofollow&quot; target=&quot;_NEW&quot;&gt;\nhttp://picturescream.com/x/clean/o1U&lt;/a&gt;\n &lt;a href=&quot;\nhttp://picturescream.com/x/clean/o1Y&quot; rel=&quot;nofollow&quot; target=&quot;_NEW&quot;&gt;\nhttp://picturescream.com/x/clean/o1Y&lt;/a&gt;\n &lt;a href=&quot;\nhttp://picturescream.com/x/clean/o1b&quot; rel=&quot;nofollow&quot; target=&quot;_NEW&quot;&gt;\nhttp://picturescream.com/x/clean/o1b&lt;/a&gt;\n\n\nVideos Info:\n~~~~~~~~~~~~\nSize: 1.071 GB\nDuration: 50:17\nResolution: 1280x720","torrent":{"xt":"urn:btih:6c66b5d12ab1a951e79e6c20360f935dbeb5d9e6","amp;dn":"College+Rules+-+Crazy+College+Orgy+HD+720p","amp;tr":["udp%3A%2F%2Ftracker.openbittorrent.com%3A80","udp%3A%2F%2Fopen.demonii.com%3A1337","udp%3A%2F%2Ftracker.coppersurfer.tk%3A6969","udp%3A%2F%2Fexodus.desync.com%3A6969"],"infoHash":"6c66b5d12ab1a951e79e6c20360f935dbeb5d9e6","infoHashBuffer":{"type":"Buffer","data":[108,102,181,209,42,177,169,81,231,158,108,32,54,15,147,93,190,181,217,230]},"announce":[],"urlList":[]}}