{"title":"{MyFriendsHotMom} Diamond Jackson {19773 - 06.15.2015} NEW June ","uid":12018934,"size":225221951,"categoryP":"porn","categoryS":"movie_clips","magnet":"?xt=urn:btih:7872f4d912d485a9128c29196ec7917c8113cba7&amp;dn=%7BMyFriendsHotMom%7D+Diamond+Jackson+%7B19773+-+06.15.2015%7D+NEW+June+&amp;tr=udp%3A%2F%2Ftracker.openbittorrent.com%3A80&amp;tr=udp%3A%2F%2Fopen.demonii.com%3A1337&amp;tr=udp%3A%2F%2Ftracker.coppersurfer.tk%3A6969&amp;tr=udp%3A%2F%2Fexodus.desync.com%3A6969","seeders":2,"leechers":0,"uploader":"coolzone1","files":1,"time":1434374581,"description":"JMac and Levi sneak into their friend's house to play a prank on him. They are out to embarrass their friend by raiding his mom's pantie drawer. Their friend's mom, Diamond Jackson, comes home early and catches them in the act. She decides since they want to see her panties so badly that she might as well just give them the pussy. Levi runs out though as he has a girlfriend, leaving JMac to bang Diamond alone","torrent":{"xt":"urn:btih:7872f4d912d485a9128c29196ec7917c8113cba7","amp;dn":"%7BMyFriendsHotMom%7D+Diamond+Jackson+%7B19773+-+06.15.2015%7D+NEW+June+","amp;tr":["udp%3A%2F%2Ftracker.openbittorrent.com%3A80","udp%3A%2F%2Fopen.demonii.com%3A1337","udp%3A%2F%2Ftracker.coppersurfer.tk%3A6969","udp%3A%2F%2Fexodus.desync.com%3A6969"],"infoHash":"7872f4d912d485a9128c29196ec7917c8113cba7","infoHashBuffer":{"type":"Buffer","data":[120,114,244,217,18,212,133,169,18,140,41,25,110,199,145,124,129,19,203,167]},"announce":[],"urlList":[]}}