{"title":"Photoshop - The Missing Manual + Exr. Files + 3D Action","uid":8047610,"size":54765888,"categoryP":"applications","categoryS":"windows","magnet":"?xt=urn:btih:8d323c1b0a621ec89b05b478ef754d84c628c29c&amp;dn=Photoshop+-+The+Missing+Manual+%2B+Exr.+Files+%2B+3D+Action&amp;tr=udp%3A%2F%2Ftracker.openbittorrent.com%3A80&amp;tr=udp%3A%2F%2Fopen.demonii.com%3A1337&amp;tr=udp%3A%2F%2Ftracker.coppersurfer.tk%3A6969&amp;tr=udp%3A%2F%2Fexodus.desync.com%3A6969","seeders":2,"leechers":1,"uploader":"promodsharma","files":1,"time":1358787500,"description":"Photoshop - The Missing Manual + Exr. Files + 3D Action :\n========================================================\n\n\n(Since the Photoshop Interface is the same in Windows and Mac OS this book can be \n\nused to learn on either OS. Differences are pointed out where ever applicable).\n\n\n\nThis  Torrent contains :\n\n\n1. Photoshop - The Missing Manual (O'Reilly) Book (816 Pages, pdf File with \n\nBookmarks - 24.5 MB) + Exercise Files (32.7 MB) + Errata File (pdf 76.8 Kb) for \n\nthe Book. Although this book is based on Photoshop Version CS 5, it fully and \n\ncompletely compatible with Photoshop CS 6.\n\n\n\nThis Book give an insight into Photoshop, normally not covered in other Photoshop \n\nBooks and discusses topics in a simple and straight forward manner, much like \n\nhaving a personal tutor !\n\n\nCONTENTS :\n////////\n\nPart One: The Basics\n--------------------\n\n1. Chapter 1: Photoshop CS5 Guided Tour\n\n2. Chapter 2: Opening, Viewing, and Saving Files\n\n3. Chapter 3: Layers: The Key to Nondestructive Editing\n\n4. Chapter 4: Selections: Choosing What to Edit\n\n5. Chapter 5: Controlling Color with Channels\n\n\nPart Two: Editing Images\n------------------------\n\n6. Chapter 6: Cropping, Resizing, and Rotating\n\n7. Chapter 7: Combining Images\n\n8. Chapter 8: Draining, Changing, and Adding Color\n\n9. Chapter 9: Correcting Color and Lighting\n\n10. Chapter 10: The Beauty Salon: Photoshopping People\n\n11. Chapter 11: The Art of Sharpening. \n\nPart Three: The Artistic Side of Photoshop\n------------------------------------------\n\n12. Chapter 12: Painting in Photoshop\n\n13. Chapter 13: Drawing with the Vector Tools\n\n14. Chapter 14: Creating Artistic Text\n\n15. Chapter 15: The Wide World of Filters\n\nPart Four: Printing and the Web\n-------------------------------\n\n16. Chapter 16: Photoshop and Print\n\n17. Chapter 17: Photoshop and the Web\n\nPart Five: Photoshop Power\n--------------------------\n\n18. Chapter 18: Working Smarter with Actions\n\n19. Chapter 19: Beyond Photoshop: Plug-Ins..\n\n\n\n2.  An  Amazing Photoshop Action (1.52 MB)  that converts your Text within \n\nPhotoshop into Blazing 3D Text  (Instructions are included). This Action is \n\ncompatible with Photoshop CS to Photoshop CS 6 and Windows OS :  Windows XP to \n\nWindows 8 - 32 Bit (May or May not work in 64 Bits).\n\n=============================================================================\n\nSEED AND ENJOY !\n\nTHE UPLOADS  ARE VIRUS / MALWARE FREE.\n\nALL CREDIT TO AN ARMY OF UPLOADERS / CRACKERS / REVERSERS\n\nLEAVE COMMENTS FOR OTHER DOWNLOADERS TO REFER.\n\nAND REMEMBER TO ENJOY ! OR THE DOWNLOADS  WON'T WORK  : )\n\n==============================================================================\n\nUNFORGIVENESS IS LIKE DRINKING POISON AND HOPING THE OTHER PERSON DIES !!!\n\n===============================================================================\n\nGOD BLESS.\n\n","torrent":{"xt":"urn:btih:8d323c1b0a621ec89b05b478ef754d84c628c29c","amp;dn":"Photoshop+-+The+Missing+Manual+%2B+Exr.+Files+%2B+3D+Action","amp;tr":["udp%3A%2F%2Ftracker.openbittorrent.com%3A80","udp%3A%2F%2Fopen.demonii.com%3A1337","udp%3A%2F%2Ftracker.coppersurfer.tk%3A6969","udp%3A%2F%2Fexodus.desync.com%3A6969"],"infoHash":"8d323c1b0a621ec89b05b478ef754d84c628c29c","infoHashBuffer":{"type":"Buffer","data":[141,50,60,27,10,98,30,200,155,5,180,120,239,117,77,132,198,40,194,156]},"announce":[],"urlList":[]}}