{"title":"Air.Crash.Investigation.S10E06.Who's.in.Control.1080i.HDTV","uid":9395936,"size":1530474267,"categoryP":"video","categoryS":"hd___tv_shows","magnet":"?xt=urn:btih:9afc194a47236944f9c8d66da01d179a59da8071&amp;dn=Air.Crash.Investigation.S10E06.Who%27s.in.Control.1080i.HDTV&amp;tr=udp%3A%2F%2Ftracker.openbittorrent.com%3A80&amp;tr=udp%3A%2F%2Fopen.demonii.com%3A1337&amp;tr=udp%3A%2F%2Ftracker.coppersurfer.tk%3A6969&amp;tr=udp%3A%2F%2Fexodus.desync.com%3A6969","seeders":2,"leechers":2,"uploader":"SquareFish","files":-1,"time":1387981283,"description":"MAYDAY / AIR CRASH INVESTIGATION\n\n1080i HDTV :D\n\n---------------------------------\n\nFILE INFO:\nDuration: 45+ minutes\nFile size: +/- 1.5GB\n\nVIDEO:\nFormat: Matroska (.mkv)\nResolution: 1920x1080\nBitrate: +/- 8000 kbps\nFramerate: 25 fps\n\nAUDIO:\nType: Stereo\nBitrate: 210 kbps\n\n---------------------------------\n\nPlease seed!!!","torrent":{"xt":"urn:btih:9afc194a47236944f9c8d66da01d179a59da8071","amp;dn":"Air.Crash.Investigation.S10E06.Who%27s.in.Control.1080i.HDTV","amp;tr":["udp%3A%2F%2Ftracker.openbittorrent.com%3A80","udp%3A%2F%2Fopen.demonii.com%3A1337","udp%3A%2F%2Ftracker.coppersurfer.tk%3A6969","udp%3A%2F%2Fexodus.desync.com%3A6969"],"infoHash":"9afc194a47236944f9c8d66da01d179a59da8071","infoHashBuffer":{"type":"Buffer","data":[154,252,25,74,71,35,105,68,249,200,214,109,160,29,23,154,89,218,128,113]},"announce":[],"urlList":[]}}