{"title":"Today I Caught the Plague - Lore (2011) CD Rip 320 kbps {Protest","uid":7466746,"size":111957002,"categoryP":"audio","categoryS":"music","magnet":"?xt=urn:btih:a2a7a825c4dc57c17064791ebde3ba1417e5ac1b&amp;dn=Today+I+Caught+the+Plague+-+Lore+%282011%29+CD+Rip+320+kbps+%7BProtest&amp;tr=udp%3A%2F%2Ftracker.openbittorrent.com%3A80&amp;tr=udp%3A%2F%2Fopen.demonii.com%3A1337&amp;tr=udp%3A%2F%2Ftracker.coppersurfer.tk%3A6969&amp;tr=udp%3A%2F%2Fexodus.desync.com%3A6969","seeders":2,"leechers":0,"uploader":"ProtestTheHero86","files":10,"time":1343020230,"description":"Today I Caught the Plague is a Canadian progressive metal that takes use of using clean vocals entirely. Today I Caught the Plague is an up and coming band that is very talented, touring with acts such as Protest the Hero.\n\nToday I Caught the Plague is:\nDavid Journeaux - Vocals\nMatt Young - Keyboards\nBen Davis - Guitar\nSteve Rennie - Guitar\nEric Stone - Bass\nMichael Ieradi - Drums\n\nTrack listing:\n1) The Consequence of Fratricide\n2) From Bulwark to Bane\n3) Cimmerian Dusk\n4) Irradiant Dawn\n5) Of Fang and Flesh\n6) Tempting Haiwa\n7) A Cluster of Rogues\n8) Sorrowbred\n9) All Gallant's Oath\n10) Origins (Of Measurable Being)\n\nSometimes my internet will randomly cut out so if I'm not seeding, that's why. Blame Charter. Any issues/concerns feel free to contact me at &lt;a class=&quot;__cf_email__&quot; href=&quot;/cdn-cgi/l/email-protection&quot; data-cfemail=&quot;accdc4cdcbc9989a9aecc4c3d8c1cdc5c082cfc3c1&quot;&gt;[email&amp;#160;protected]&lt;/a&gt;&lt;script cf-hash='f9e31' type=&quot;text/javascript&quot;&gt;\n/* &lt;![CDATA[ */!function(){try{var t=&quot;currentScript&quot;in document?document.currentScript:function(){for(var t=document.getElementsByTagName(&quot;script&quot;),e=t.length;e--;)if(t[e].getAttribute(&quot;cf-hash&quot;))return t[e]}();if(t&amp;&amp;t.previousSibling){var e,r,n,i,c=t.previousSibling,a=c.getAttribute(&quot;data-cfemail&quot;);if(a){for(e=&quot;&quot;,r=parseInt(a.substr(0,2),16),n=2;a.length-n;n+=2)i=parseInt(a.substr(n,2),16)^r,e+=String.fromCharCode(i);e=document.createTextNode(e),c.parentNode.replaceChild(e,c)}}}catch(u){}}();/* ]]&gt; */&lt;/script&gt;, which I shall check regularly. Feel free to send requests, but I don't have an intention to upload a lot, just whatever I feel like is worth sharing. Please seed and feedback is very much appreciated.","torrent":{"xt":"urn:btih:a2a7a825c4dc57c17064791ebde3ba1417e5ac1b","amp;dn":"Today+I+Caught+the+Plague+-+Lore+%282011%29+CD+Rip+320+kbps+%7BProtest","amp;tr":["udp%3A%2F%2Ftracker.openbittorrent.com%3A80","udp%3A%2F%2Fopen.demonii.com%3A1337","udp%3A%2F%2Ftracker.coppersurfer.tk%3A6969","udp%3A%2F%2Fexodus.desync.com%3A6969"],"infoHash":"a2a7a825c4dc57c17064791ebde3ba1417e5ac1b","infoHashBuffer":{"type":"Buffer","data":[162,167,168,37,196,220,87,193,112,100,121,30,189,227,186,20,23,229,172,27]},"announce":[],"urlList":[]}}