{"title":"Passion-HD - Katrin Tequila (Oil and Ecstasy) NEW 10 September 2","uid":15800543,"size":489480068,"categoryP":"porn","categoryS":"movie_clips","magnet":"?xt=urn:btih:b40d9ddba5b84e0e10a41362b3fb2974f66dc36b&amp;dn=Passion-HD+-+Katrin+Tequila+%28Oil+and+Ecstasy%29+NEW+10+September+2&amp;tr=udp%3A%2F%2Ftracker.leechers-paradise.org%3A6969&amp;tr=udp%3A%2F%2Fzer0day.ch%3A1337&amp;tr=udp%3A%2F%2Fopen.demonii.com%3A1337&amp;tr=udp%3A%2F%2Ftracker.coppersurfer.tk%3A6969&amp;tr=udp%3A%2F%2Fexodus.desync.com%3A6969","seeders":2,"leechers":1,"uploader":"xxxlavalxxx","files":2,"time":1473496810,"description":"Passion-HD - Katrin Tequila (Oil and Ecstasy) NEW 10 September 2016\r\n\r\nTags: All Sex, Anal, Blowjob, Blonde, Big Dick, Hardcore, Oil\r\n \nhttp://imgdone.com/viewer.php?file=50363718522485283145.jpg\r\n \nhttp://imgdone.com/viewer.php?file=61793290599194478460.jpg","torrent":{"xt":"urn:btih:b40d9ddba5b84e0e10a41362b3fb2974f66dc36b","amp;dn":"Passion-HD+-+Katrin+Tequila+%28Oil+and+Ecstasy%29+NEW+10+September+2","amp;tr":["udp%3A%2F%2Ftracker.leechers-paradise.org%3A6969","udp%3A%2F%2Fzer0day.ch%3A1337","udp%3A%2F%2Fopen.demonii.com%3A1337","udp%3A%2F%2Ftracker.coppersurfer.tk%3A6969","udp%3A%2F%2Fexodus.desync.com%3A6969"],"infoHash":"b40d9ddba5b84e0e10a41362b3fb2974f66dc36b","infoHashBuffer":{"type":"Buffer","data":[180,13,157,219,165,184,78,14,16,164,19,98,179,251,41,116,246,109,195,107]},"announce":[],"urlList":[]}}