{"title":"Brazzers: Jenna Sativa and Vanessa Veracruz - But I'm Straight!","uid":15766513,"size":500657949,"categoryP":"porn","categoryS":"movie_clips","magnet":"?xt=urn:btih:d123ce1209b81ca91df6cf0cd245cf020b5a70d3&amp;dn=Brazzers%3A+Jenna+Sativa+and+Vanessa+Veracruz+-+But+I%27m+Straight%21&amp;tr=udp%3A%2F%2Ftracker.leechers-paradise.org%3A6969&amp;tr=udp%3A%2F%2Fzer0day.ch%3A1337&amp;tr=udp%3A%2F%2Fopen.demonii.com%3A1337&amp;tr=udp%3A%2F%2Ftracker.coppersurfer.tk%3A6969&amp;tr=udp%3A%2F%2Fexodus.desync.com%3A6969","seeders":2,"leechers":0,"uploader":"SudoSu","files":1,"time":1473153847,"description":"-------------------------\r\n ... : Screenshots : ... \r\n-------------------------\r\n \nhttp://imagep2p.com/?v=864687 \nhttp://imagep2p.com/?g=650215\r\n\r\n-------------------------\r\n ... : Description : ... \r\n-------------------------\r\n\r\n[HotAndMean - Brazzers] Jenna Sativa and Vanessa Veracruz (But I'm Straight! - 06.09.16) NEW\r\n\r\nActress Name: Jenna Sativa &amp; Vanessa Veracruz\r\nName movie: But I'm Straight!\r\nSubsites and site: HotAndMean / Brazzers\r\n\r\nProduction year: 2016\r\nGenre: Big Tits, Big Tits Worship, Brunette, Cheating, Couples Fantasies, Latina, Lesbian, Natural Tits\r\nDuration: 00:31:08\r\n\r\nVideo Quality: SiteRip\r\nVideo Format: MP4\r\nVideo: MPEG4 Video (H264) 854x480 29.97fps 2000kbps\r\nAudio: AAC 48000Hz stereo 127kbps\r\n\r\nMore exclusive porn at:  https://thepiratebay.se/user/SudoSu/\r\n\r  http://youpornbook.com","torrent":{"xt":"urn:btih:d123ce1209b81ca91df6cf0cd245cf020b5a70d3","amp;dn":"Brazzers%3A+Jenna+Sativa+and+Vanessa+Veracruz+-+But+I%27m+Straight%21","amp;tr":["udp%3A%2F%2Ftracker.leechers-paradise.org%3A6969","udp%3A%2F%2Fzer0day.ch%3A1337","udp%3A%2F%2Fopen.demonii.com%3A1337","udp%3A%2F%2Ftracker.coppersurfer.tk%3A6969","udp%3A%2F%2Fexodus.desync.com%3A6969"],"infoHash":"d123ce1209b81ca91df6cf0cd245cf020b5a70d3","infoHashBuffer":{"type":"Buffer","data":[209,35,206,18,9,184,28,169,29,246,207,12,210,69,207,2,11,90,112,211]},"announce":[],"urlList":[]}}