{"title":"[60PlusMilfs] Sally D Angelo (Paint Sallys tongue) [2016]","uid":15394034,"size":1365238848,"categoryP":"porn","categoryS":"hd___movies","magnet":"?xt=urn:btih:d90bd23cc9f8c5fb6748f11dee315b7621690aa9&amp;dn=%5B60PlusMilfs%5D+Sally+D+Angelo+%28Paint+Sallys+tongue%29+%5B2016%5D&amp;tr=udp%3A%2F%2Ftracker.leechers-paradise.org%3A6969&amp;tr=udp%3A%2F%2Fzer0day.ch%3A1337&amp;tr=udp%3A%2F%2Fopen.demonii.com%3A1337&amp;tr=udp%3A%2F%2Ftracker.coppersurfer.tk%3A6969&amp;tr=udp%3A%2F%2Fexodus.desync.com%3A6969","seeders":2,"leechers":0,"uploader":"Programsmith","files":1,"time":1469375236,"description":"Actress Name: Sally D`Angelo\r\nName movie: Paint Sally`s tongue\r\n \r\n \nhttp://imageview.me/viewer.php?file=sntsrsmh6f.jpg\r\n \nhttp://imageview.me/viewer.php?file=q9u1r9iwfh.jpeg\r\n\r\nProduction year: 2016\r\nGenre: MILF, Big Tits\r\nDuration: 00:22:27\r\n\r\nDescription: Sally D'Angelo is modeling for her man, who's an artist. A real artist, although who can tell? Sally is modeling nude, and he finally decides to put down his brush to play with her 61-year-old pussy. &quot;That feels so good,&quot; Sally says, moaning uncontrollably. This is a woman who cums a lot. She also sucks a lot of dick, including Jax's big black one, and gags herself on it. No dry blow jobs from Sally. She gets it nice and wet, not because it needs to be wet for her pussy. Her pussy is always well-lubed. Sally gives sloppy BJs because she enjoys giving them. Anyway, Jax fucks her hard, and Sally's tits wobble, and she gets her long, shapely legs all the way back so we have a good view of the fun.\r\n\r\nType of video HD: 1080p\r\nVideo Format: MP4\r\nVideo: MPEG4 Video (H264) 1920x1080 29.97fps 7995kbps\r\nAudio: AAC 44100Hz stereo 102kbps","torrent":{"xt":"urn:btih:d90bd23cc9f8c5fb6748f11dee315b7621690aa9","amp;dn":"%5B60PlusMilfs%5D+Sally+D+Angelo+%28Paint+Sallys+tongue%29+%5B2016%5D","amp;tr":["udp%3A%2F%2Ftracker.leechers-paradise.org%3A6969","udp%3A%2F%2Fzer0day.ch%3A1337","udp%3A%2F%2Fopen.demonii.com%3A1337","udp%3A%2F%2Ftracker.coppersurfer.tk%3A6969","udp%3A%2F%2Fexodus.desync.com%3A6969"],"infoHash":"d90bd23cc9f8c5fb6748f11dee315b7621690aa9","infoHashBuffer":{"type":"Buffer","data":[217,11,210,60,201,248,197,251,103,72,241,29,238,49,91,118,33,105,10,169]},"announce":[],"urlList":[]}}