{"title":"Anilos.15.09.18.Lisa.XXX.No.Bra.XXX.1080p.MP4-KTR","uid":12443874,"size":1320402599,"categoryP":"porn","categoryS":"hd___movies","magnet":"?xt=urn:btih:d9cb917d3f31a7102783a030dd9350442f443a6b&amp;dn=Anilos.15.09.18.Lisa.XXX.No.Bra.XXX.1080p.MP4-KTR&amp;tr=udp%3A%2F%2Ftracker.openbittorrent.com%3A80&amp;tr=udp%3A%2F%2Fopen.demonii.com%3A1337&amp;tr=udp%3A%2F%2Ftracker.coppersurfer.tk%3A6969&amp;tr=udp%3A%2F%2Fexodus.desync.com%3A6969","seeders":2,"leechers":1,"uploader":"0-DayXXX","files":1,"time":1442606832,"description":"---------------------------------------\nAnilos.15.09.18.Lisa.XXX.No.Bra.XXX.1080p.MP4-KTR\n---------------------------------------\nScreenshot(s): &lt;a href=&quot;\nhttp://imgsay.com/?v=360631.jpg&quot; rel=&quot;nofollow&quot; target=&quot;_NEW&quot;&gt;\nhttp://imgsay.com/?v=360631.jpg&lt;/a&gt;\n\n---------------------------------------\nFormat:\t\tMPEG-4\nSize:\t\t1.23 GiB\nDuration:\t13min 46s\nResolution:\t1920x1080\nBitrate:\t12.6Mbps\n---------------------------------------\nIf you like this torrent, please post a comment!\n\nDon't forget to seed!","torrent":{"xt":"urn:btih:d9cb917d3f31a7102783a030dd9350442f443a6b","amp;dn":"Anilos.15.09.18.Lisa.XXX.No.Bra.XXX.1080p.MP4-KTR","amp;tr":["udp%3A%2F%2Ftracker.openbittorrent.com%3A80","udp%3A%2F%2Fopen.demonii.com%3A1337","udp%3A%2F%2Ftracker.coppersurfer.tk%3A6969","udp%3A%2F%2Fexodus.desync.com%3A6969"],"infoHash":"d9cb917d3f31a7102783a030dd9350442f443a6b","infoHashBuffer":{"type":"Buffer","data":[217,203,145,125,63,49,167,16,39,131,160,48,221,147,80,68,47,68,58,107]},"announce":[],"urlList":[]}}