{"title":"Textile processing with enzymes.pdf","uid":11411164,"size":2769658,"categoryP":"other","categoryS":"e_books","magnet":"?xt=urn:btih:edad5f70cc7c185abaf5dbb1e35db93d884f2b7c&amp;dn=Textile+processing+with+enzymes.pdf&amp;tr=udp%3A%2F%2Ftracker.openbittorrent.com%3A80&amp;tr=udp%3A%2F%2Fopen.demonii.com%3A1337&amp;tr=udp%3A%2F%2Ftracker.coppersurfer.tk%3A6969&amp;tr=udp%3A%2F%2Fexodus.desync.com%3A6969","seeders":2,"leechers":0,"uploader":"ferdgust","files":1,"time":1415492758,"description":"","torrent":{"xt":"urn:btih:edad5f70cc7c185abaf5dbb1e35db93d884f2b7c","amp;dn":"Textile+processing+with+enzymes.pdf","amp;tr":["udp%3A%2F%2Ftracker.openbittorrent.com%3A80","udp%3A%2F%2Fopen.demonii.com%3A1337","udp%3A%2F%2Ftracker.coppersurfer.tk%3A6969","udp%3A%2F%2Fexodus.desync.com%3A6969"],"infoHash":"edad5f70cc7c185abaf5dbb1e35db93d884f2b7c","infoHashBuffer":{"type":"Buffer","data":[237,173,95,112,204,124,24,90,186,245,219,177,227,93,185,61,136,79,43,124]},"announce":[],"urlList":[]}}